chopperfix/__init__.py
chopperfix/chopper_decorators.py
learning/__init__.py
learning/pattern_storage.py
llm_integration/__init__.py
llm_integration/adalflow_manager.py
llm_integration/langchain_manager.py
self_healing/__init__.py
utils/__init__.py
utils/config.py
ChopperFix-0.1.2.dist-info/METADATA
ChopperFix-0.1.2.dist-info/WHEEL
ChopperFix-0.1.2.dist-info/top_level.txt
ChopperFix-0.1.2.dist-info/RECORD
