Metadata-Version: 2.1
Name: ChopperFix
Version: 0.1.2
Summary: Librería de self-healing para automatización web con análisis y reconocimiento de patrones
Home-page: https://github.com/hugoguerrap/ChopperFix.git
Author: Hugo Guerra
Author-email: 
Classifier: Programming Language :: Python :: 3
Classifier: License :: OSI Approved :: MIT License
Classifier: Operating System :: OS Independent
Requires-Python: >=3.6
Requires-Dist: sqlalchemy
Requires-Dist: playwright
Requires-Dist: beautifulsoup4
Requires-Dist: adalflow
Requires-Dist: openai
Requires-Dist: selenium
Requires-Dist: Pillow
Requires-Dist: requests
Requires-Dist: pydantic
Requires-Dist: loguru
Requires-Dist: numpy
Requires-Dist: scikit-learn
